SimExLite/PhotonBeamData.py
SimExLite/SampleData.py
SimExLite/SimExLite.py
SimExLite/__init__.py
SimExLite/cli.py
SimExLite/DetectorCalculators/GaussianNoiseCalculator.py
SimExLite/DetectorCalculators/__init__.py
SimExLite/DiffractionCalculators/SingFELDiffractionCalculator.py
SimExLite/DiffractionCalculators/__init__.py
SimExLite/DiffractionData/DiffractionData.py
SimExLite/DiffractionData/EMCPhoton.py
SimExLite/DiffractionData/SingFELFormat.py
SimExLite/DiffractionData/__init__.py
SimExLite/DiffractionData/singfelDiffr.py
SimExLite/DiffractionData/writeemc.py
SimExLite/PMICalculators/SimpleScatteringPMICalculator.py
SimExLite/PMICalculators/__init__.py
SimExLite/PMIData/PMIData.py
SimExLite/PMIData/XMDYNFormat.py
SimExLite/PMIData/__init__.py
SimExLite/PropagationCalculators/WPGPropagationCalculator.py
SimExLite/PropagationCalculators/__init__.py
SimExLite/SampleData/ASEFormat.py
SimExLite/SampleData/SampleData.py
SimExLite/SampleData/__init__.py
SimExLite/SourceCalculators/GaussianSourceCalculator.py
SimExLite/SourceCalculators/__init__.py
SimExLite/WavefrontData/WPGFormat.py
SimExLite/WavefrontData/WavefrontData.py
SimExLite/WavefrontData/__init__.py
SimExLite/utils/Logger.py
SimExLite/utils/__init__.py
SimExLite/utils/analysis.py
SimExLite/utils/io.py
SimEx_Lite-1.0.0.dist-info/AUTHORS.rst
SimEx_Lite-1.0.0.dist-info/LICENSE
SimEx_Lite-1.0.0.dist-info/METADATA
SimEx_Lite-1.0.0.dist-info/WHEEL
SimEx_Lite-1.0.0.dist-info/entry_points.txt
SimEx_Lite-1.0.0.dist-info/top_level.txt
SimEx_Lite-1.0.0.dist-info/RECORD
