Metadata-Version: 2.1
Name: SimEx-Lite
Version: 1.0.0
Summary: The core package of the SIMEX platform providing the calculator interfaces.
Home-page: https://github.com/PaNOSC-ViNYL/SimEx-Lite
Author: Juncheng E
Author-email: juncheng.e@xfel.eu
License: GNU General Public License v3
Keywords: SimEx-Lite
Platform: UNKNOWN
Classifier: Development Status :: 2 - Pre-Alpha
Classifier: Intended Audience :: Developers
Classifier: License :: OSI Approved :: GNU General Public License v3 (GPLv3)
Classifier: Natural Language :: English
Classifier: Programming Language :: Python :: 3
Classifier: Programming Language :: Python :: 3.6
Classifier: Programming Language :: Python :: 3.7
Classifier: Programming Language :: Python :: 3.8
Requires-Python: >=3.6
License-File: LICENSE
License-File: AUTHORS.rst
Requires-Dist: numpy
Requires-Dist: matplotlib
Requires-Dist: scipy
Requires-Dist: h5py
Requires-Dist: ase
Requires-Dist: pint
Requires-Dist: future-fstrings
Requires-Dist: libpyvinyl (>=0.1.0)
Requires-Dist: extra-geom (>=1.1)
